{"trial_id": "17", "hyperparameters": {"space": [{"class_name": "Choice", "config": {"name": "layers", "default": 1, "conditions": [], "values": [1, 2], "ordered": true}}, {"class_name": "Choice", "config": {"name": "filters", "default": 32, "conditions": [], "values": [32, 64, 128], "ordered": true}}, {"class_name": "Choice", "config": {"name": "activation", "default": "relu", "conditions": [], "values": ["relu", "tanh", "sigmoid"], "ordered": false}}, {"class_name": "Choice", "config": {"name": "optimizer", "default": "adam", "conditions": [], "values": ["adam", "rmsprop"], "ordered": false}}, {"class_name": "Choice", "config": {"name": "learning_rate", "default": 0.01, "conditions": [], "values": [0.01, 0.001], "ordered": true}}], "values": {"layers": 1, "filters": 64, "activation": "tanh", "optimizer": "adam", "learning_rate": 0.001}}, "metrics": {"metrics": {"loss": {"direction": "min", "observations": [{"value": [0.0062474352307617664], "step": 71}]}, "mae": {"direction": "min", "observations": [{"value": [0.0627555400133133], "step": 71}]}, "val_loss": {"direction": "min", "observations": [{"value": [0.0050032478757202625], "step": 71}]}, "val_mae": {"direction": "min", "observations": [{"value": [0.05603542923927307], "step": 71}]}}}, "score": 0.0050032478757202625, "best_step": 71, "status": "COMPLETED", "message": null}