{"trial_id": "51", "hyperparameters": {"space": [{"class_name": "Choice", "config": {"name": "layers", "default": 1, "conditions": [], "values": [1, 2], "ordered": true}}, {"class_name": "Choice", "config": {"name": "filters", "default": 32, "conditions": [], "values": [32, 64, 128], "ordered": true}}, {"class_name": "Choice", "config": {"name": "activation", "default": "relu", "conditions": [], "values": ["relu", "tanh", "sigmoid"], "ordered": false}}, {"class_name": "Choice", "config": {"name": "optimizer", "default": "adam", "conditions": [], "values": ["adam", "rmsprop"], "ordered": false}}, {"class_name": "Choice", "config": {"name": "learning_rate", "default": 0.01, "conditions": [], "values": [0.01, 0.001], "ordered": true}}], "values": {"layers": 2, "filters": 64, "activation": "relu", "optimizer": "rmsprop", "learning_rate": 0.001}}, "metrics": {"metrics": {"loss": {"direction": "min", "observations": [{"value": [0.0018728936556726694], "step": 111}]}, "mae": {"direction": "min", "observations": [{"value": [0.03362303227186203], "step": 111}]}, "val_loss": {"direction": "min", "observations": [{"value": [0.0009738806402310729], "step": 111}]}, "val_mae": {"direction": "min", "observations": [{"value": [0.02268802747130394], "step": 111}]}}}, "score": 0.0009738806402310729, "best_step": 111, "status": "COMPLETED", "message": null}