{"trial_id": "26", "hyperparameters": {"space": [{"class_name": "Choice", "config": {"name": "layers", "default": 1, "conditions": [], "values": [1, 2], "ordered": true}}, {"class_name": "Choice", "config": {"name": "filters", "default": 32, "conditions": [], "values": [32, 64, 128], "ordered": true}}, {"class_name": "Choice", "config": {"name": "activation", "default": "relu", "conditions": [], "values": ["relu", "tanh", "sigmoid"], "ordered": false}}, {"class_name": "Choice", "config": {"name": "optimizer", "default": "adam", "conditions": [], "values": ["adam", "rmsprop"], "ordered": false}}, {"class_name": "Choice", "config": {"name": "learning_rate", "default": 0.01, "conditions": [], "values": [0.01, 0.001], "ordered": true}}], "values": {"layers": 1, "filters": 128, "activation": "relu", "optimizer": "rmsprop", "learning_rate": 0.01}}, "metrics": {"metrics": {"loss": {"direction": "min", "observations": [{"value": [0.007304287049919367], "step": 24}]}, "mae": {"direction": "min", "observations": [{"value": [0.06786563992500305], "step": 24}]}, "val_loss": {"direction": "min", "observations": [{"value": [0.005620977375656366], "step": 24}]}, "val_mae": {"direction": "min", "observations": [{"value": [0.05928894132375717], "step": 24}]}}}, "score": 0.005620977375656366, "best_step": 24, "status": "COMPLETED", "message": null}